dsp_toolkit/__init__.py
dsp_toolkit/cli.py
dsp_toolkit/env.py
dsp_toolkit/logging_config.py
dsp3_toolkit-1.0.1.dist-info/METADATA
dsp3_toolkit-1.0.1.dist-info/WHEEL
dsp3_toolkit-1.0.1.dist-info/entry_points.txt
dsp3_toolkit-1.0.1.dist-info/RECORD
