Metadata-Version: 2.3
Name: dsp3-toolkit
Version: 1.0.1
Summary: DSP shared toolkit for Python apps: CLI, logging, config, linting, plugins, and more.
Author: Mark Small
Author-email: marksmall@gmx.com
Requires-Python: >=3.12,<4.0
Classifier: Programming Language :: Python :: 3
Classifier: Programming Language :: Python :: 3.12
Classifier: Programming Language :: Python :: 3.13
Requires-Dist: dotenv (>=0.9.9,<0.10.0)
Requires-Dist: flake8 (>=7.3.0,<8.0.0)
Requires-Dist: flake8-awesome (>=1.3.0,<2.0.0)
Requires-Dist: flake8-bugbear (>=24.4.26,<25.0.0)
Requires-Dist: flake8-comprehensions (>=3.14.0,<4.0.0)
Requires-Dist: flake8-simplify (>=0.21.0,<0.22.0)
